[
    {
        "channel_id": "756734432",
        "channel_name": "abrokecube",
        "rf_query_url": "http://127.0.0.1:8888/ravenfall",
        "custom_town_msg": "- Streaming 24/7",
        "ravenbot_prefix": "!",
        "welcome_message": "FeelsOkayMan welcome to my {townSkillLower} town! for faster levelling, enable auto resting using \"!auto rest\" (costs 10,800 coins for a full rest)",
        "sandboxie_box": "Box0",
        "ravenfall_start_script": "start /affinity 0x8 /low Ravenfall.exe -single-instance -force-d3d11",
        "auto_restart": true,
        "event_notifications": true,
        "restart_period": 259200,
        "middleman_connection_id": "127.0.0.1_8040_4040",
        "ravenfall_loc_strings_path": "C:/Users/borkedcube/stuff/rf_strings/strings-abrokecube.yaml",
        "auto_restore_raids": false,
        "channel_points_redeems": true,
        "pause_monitoring": false
    },
    {
        "channel_id": "1253884011",
        "channel_name": "borkedcube",
        "rf_query_url": "http://127.0.0.1:8889/ravenfall",
        "custom_town_msg": "",
        "ravenbot_prefix": "!",
        "welcome_message": "FeelsOkayMan welcome to my {townSkillLower} town! for faster levelling, enable auto resting using \"!auto rest\" (costs 10,800 coins for a full rest)",
        "sandboxie_box": "Box1",
        "ravenfall_start_script": "start /affinity 0x1 /low Ravenfall.exe -nographics -batchmode -single-instance",
        "auto_restart": true,
        "event_notifications": false,
        "restart_period": 259800,
        "middleman_connection_id": "127.0.0.1_8041_4041",
        "ravenfall_loc_strings_path": "C:/Users/borkedcube/stuff/rf_strings/strings1.yaml",
        "auto_restore_raids": false,
        "pause_monitoring": false
    },
    {
        "channel_id": "1254977587",
        "channel_name": "corpsedcube",
        "rf_query_url": "http://127.0.0.1:8890/ravenfall",
        "custom_town_msg": "",
        "ravenbot_prefix": "!",
        "welcome_message": "FeelsOkayMan welcome to my {townSkillLower} town! for faster levelling, enable auto resting using \"!auto rest\" (costs 10,800 coins for a full rest)",
        "sandboxie_box": "Box2",
        "ravenfall_start_script": "start /affinity 0x2 /low Ravenfall.exe -nographics -batchmode -single-instance",
        "auto_restart": true,
        "event_notifications": true,
        "restart_period": 10860,
        "middleman_connection_id": "127.0.0.1_8042_4042",
        "ravenfall_loc_strings_path": "C:/Users/borkedcube/stuff/rf_strings/strings1.yaml",
        "auto_restore_raids": false,
        "pause_monitoring": false
    },
    {
        "channel_id": "1255781080",
        "channel_name": "dwarfedcube",
        "rf_query_url": "http://127.0.0.1:8891/ravenfall",
        "custom_town_msg": "",
        "ravenbot_prefix": "!",
        "welcome_message": "FeelsOkayMan welcome to my {townSkillLower} town! for faster levelling, enable auto resting using \"!auto rest\" (costs 10,800 coins for a full rest)",
        "sandboxie_box": "Box3",
        "ravenfall_start_script": "start /affinity 0x4 /low Ravenfall.exe -nographics -batchmode -single-instance",
        "auto_restart": true,
        "event_notifications": false,
        "restart_period": 260400,
        "middleman_connection_id": "127.0.0.1_8043_4043",
        "ravenfall_loc_strings_path": "C:/Users/borkedcube/stuff/rf_strings/strings1.yaml",
        "auto_restore_raids": false,
        "pause_monitoring": false
    }
]